amqpez/__init__.py
amqpez/amqpez.py
amqpez/amqpezconfig.py
amqpez/configbuilder.py
AMQPEz-1.0.0.dist-info/METADATA
AMQPEz-1.0.0.dist-info/WHEEL
AMQPEz-1.0.0.dist-info/top_level.txt
AMQPEz-1.0.0.dist-info/RECORD
