Metadata-Version: 2.1
Name: AMQPEz
Version: 1.0.0
Summary: Micro library to spin up AMQP shoveling with transforms
Home-page: https://github.com/frozaken/AMQPEz
Author: Marcus Teller
Author-email: marcumail@gmail.com
License: UNKNOWN
Project-URL: Bug Tracker, https://github.com/frozaken/AMQPEz/issues
Platform: UNKNOWN
Classifier: Programming Language :: Python :: 3
Classifier: License :: OSI Approved :: MIT License
Classifier: Operating System :: OS Independent
Requires-Python: >=3.5
Requires-Dist: pika
